vmsshgen/__init__.py
vmsshgen/helpers.py
vmsshgen/vmsshgen.py
vmsshgen-1.0.2.dist-info/LICENSE
vmsshgen-1.0.2.dist-info/METADATA
vmsshgen-1.0.2.dist-info/WHEEL
vmsshgen-1.0.2.dist-info/entry_points.txt
vmsshgen-1.0.2.dist-info/top_level.txt
vmsshgen-1.0.2.dist-info/RECORD
