Metadata-Version: 2.1
Name: vmsshgen
Version: 1.0.2
Summary: Automatic generation of SSH keys for VM
Home-page: https://github.com/dimon222/py-vmsshgen
Author: Dmitry Romanenko
Author-email: Dmitry@Romanenko.in
License: Apache License 2.0
Classifier: License :: OSI Approved :: Apache Software License
Classifier: Topic :: Security :: Cryptography
Classifier: Environment :: Console
Classifier: Programming Language :: Python
Classifier: Programming Language :: Python :: 3
Classifier: Operating System :: OS Independent
Requires-Python: >=3.6
License-File: LICENSE
Requires-Dist: asyncssh
